boumwave/__init__.py
boumwave/cli.py
boumwave/config.py
boumwave/exceptions.py
boumwave/models.py
boumwave/validation.py
boumwave/commands/__init__.py
boumwave/commands/generate.py
boumwave/commands/generate_now.py
boumwave/commands/generate_sitemap.py
boumwave/commands/init.py
boumwave/commands/new_now.py
boumwave/commands/new_post.py
boumwave/commands/scaffold.py
boumwave/generation/__init__.py
boumwave/generation/index_manager.py
boumwave/generation/metadata.py
boumwave/generation/parsers.py
boumwave/generation/renderers.py
boumwave/generation/sitemap_manager.py
boumwave/generation/template_engine.py
boumwave/templates/default_config.toml
boumwave/templates/example_index.html
boumwave/templates/example_link.html
boumwave/templates/example_now.html
boumwave/templates/example_now_index.html
boumwave/templates/example_post.html
boumwave/templates/example_sitemap.xml
boumwave/templates/now_template.md
boumwave/templates/post_template.md
boumwave-2.1.2.dist-info/licenses/LICENSE
boumwave-2.1.2.dist-info/METADATA
boumwave-2.1.2.dist-info/WHEEL
boumwave-2.1.2.dist-info/entry_points.txt
boumwave-2.1.2.dist-info/top_level.txt
boumwave-2.1.2.dist-info/RECORD
