Metadata-Version: 2.4
Name: BoumWave
Version: 2.1.2
Summary: The static blog generator that does exactly what it needs to. Nothing more.
Author-email: Cedric Raison <cedric.raison@hey.com>
License-Expression: MIT
Project-URL: Homepage, https://github.com/CedricRaison/BoumWave
Project-URL: Repository, https://github.com/CedricRaison/BoumWave
Project-URL: Issues, https://github.com/CedricRaison/BoumWave/issues
Keywords: static-site-generator,blog,markdown,seo,multilingual
Classifier: Development Status :: 5 - Production/Stable
Classifier: Intended Audience :: Developers
Classifier: Programming Language :: Python :: 3
Classifier: Programming Language :: Python :: 3.13
Classifier: Topic :: Internet :: WWW/HTTP :: Site Management
Classifier: Topic :: Software Development :: Code Generators
Requires-Python: >=3.13
License-File: LICENSE
Requires-Dist: ruff>=0.14.1
Requires-Dist: pydantic>=2.10.4
Requires-Dist: jinja2>=3.1.0
Requires-Dist: markdown>=3.5.0
Requires-Dist: python-frontmatter>=1.1.0
Requires-Dist: beautifulsoup4>=4.12.0
Requires-Dist: babel>=2.17.0
Provides-Extra: test
Requires-Dist: pytest>=8.0.0; extra == "test"
Requires-Dist: pytest-cov>=4.1.0; extra == "test"
Requires-Dist: pytest-mock>=3.12.0; extra == "test"
Dynamic: license-file
